README.md
license.txt
setup.py
pro_video_ferramentas_w/__init__.py
pro_video_ferramentas_w/camera.py
pro_video_ferramentas_w/video.py
pro_video_ferramentas_w.egg-info/PKG-INFO
pro_video_ferramentas_w.egg-info/SOURCES.txt
pro_video_ferramentas_w.egg-info/dependency_links.txt
pro_video_ferramentas_w.egg-info/top_level.txt