Metadata-Version: 2.1
Name: pro-video-ferramentas-w
Version: 1.0
Summary: Teste: Este pacote irá fornecer ferramentas de processamento de vídeo
Author: Wevanny de S. Gomes
Author-email: wevannytest@hotmail.com
Keywords: camera,video,processamento
License-File: license.txt
